imperium_legacy/__init__.py
imperium_legacy/evaluator.py
imperium_legacy/exceptions.py
imperium_legacy/helpers.py
imperium_legacy-0.0.5.dist-info/METADATA
imperium_legacy-0.0.5.dist-info/WHEEL
imperium_legacy-0.0.5.dist-info/top_level.txt
imperium_legacy-0.0.5.dist-info/RECORD
