Metadata-Version: 2.1
Name: imperium-legacy
Version: 0.0.5
Summary: Imperium is a python package that allows you to easily evaluate python expressions
Home-page: https://github.com/ibragim64/imperium
Author: Ibragim Abubakarov
Author-email: ibragim.ai95@gmail.com
Maintainer: Ibragim Abubakarov
Maintainer-email: ibragim.ai95@gmail.com
License: UNKNOWN
Platform: UNKNOWN
Classifier: Programming Language :: Python :: 3
Classifier: Operating System :: OS Independent
Classifier: Intended Audience :: Developers
